pyflow/__init__.py
pyflow/cache.py
pyflow/icon.py
pyflow/item.py
pyflow/testing.py
pyflow/workflow.py
alfred_pyflow-0.4.8.dist-info/WHEEL
alfred_pyflow-0.4.8.dist-info/METADATA
alfred_pyflow-0.4.8.dist-info/RECORD
