Metadata-Version: 2.1
Name: alfred-pyflow
Version: 0.4.8
Summary: Minimal library for the development of Alfred Workflows.
Home-page: https://github.com/fedecalendino/alfred-pyflow
License: MIT
Keywords: alfred,workflow
Author: Fede Calendino
Author-email: fede@calendino.com
Requires-Python: >=3.8,<4.0
Classifier: Intended Audience :: Developers
Classifier: License :: OSI Approved :: MIT License
Classifier: Programming Language :: Python :: 3
Classifier: Programming Language :: Python :: 3.8
Classifier: Programming Language :: Python :: 3.9
Classifier: Programming Language :: Python :: 3.10
Classifier: Programming Language :: Python :: 3.11
Classifier: Programming Language :: Python :: 3.10
Classifier: Programming Language :: Python :: 3.11
Classifier: Programming Language :: Python :: 3.8
Classifier: Programming Language :: Python :: 3.9
Requires-Dist: requests (>=2.30.0,<3.0.0)
Requires-Dist: urllib3 (==2.2.1)
Project-URL: Documentation, https://github.com/fedecalendino/alfred-pyflow/blob/main/README.md
